relation_client/__init__.py
relation_client/client.py
relation_client/constants.py
relation_client/exceptions.py
relation_client/models.py
relation_client/resources/__init__.py
relation_client/resources/attachments.py
relation_client/resources/badges.py
relation_client/resources/case_categories.py
relation_client/resources/chats.py
relation_client/resources/customer_groups.py
relation_client/resources/customers.py
relation_client/resources/labels.py
relation_client/resources/mail_accounts.py
relation_client/resources/mails.py
relation_client/resources/message_boxes.py
relation_client/resources/pending_reasons.py
relation_client/resources/templates.py
relation_client/resources/tickets.py
relation_client/resources/users.py
relation_client/tests/__init__.py
relation_client/tests/test_attachment_resource.py
relation_client/tests/test_badge_resource.py
relation_client/tests/test_case_category_resource.py
relation_client/tests/test_chat_resource.py
relation_client/tests/test_client.py
relation_client/tests/test_customer_group_resource.py
relation_client/tests/test_customer_resource.py
relation_client/tests/test_label_resource.py
relation_client/tests/test_mail_account_resource.py
relation_client/tests/test_mail_resource.py
relation_client/tests/test_message_box_resource.py
relation_client/tests/test_pending_reason_resource.py
relation_client/tests/test_template_resource.py
relation_client/tests/test_ticket_resource.py
relation_client/tests/test_user_resource.py
relation_client-0.1.0.dist-info/LICENSE
relation_client-0.1.0.dist-info/METADATA
relation_client-0.1.0.dist-info/WHEEL
relation_client-0.1.0.dist-info/top_level.txt
relation_client-0.1.0.dist-info/RECORD
