Metadata-Version: 2.2
Name: relation-client
Version: 0.1.0
Summary: Re:lation API Python クライアントライブラリ
Home-page: https://github.com/solahsoyalp/relation_client
Author: solah soyalp
Author-email: solah.soyalp@gmail.com
Project-URL: Bug Reports, https://github.com/solahsoyalp/relation_client/issues
Project-URL: Source, https://github.com/solahsoyalp/relation_client
Classifier: Development Status :: 3 - Alpha
Classifier: Intended Audience :: Developers
Classifier: License :: OSI Approved :: MIT License
Classifier: Programming Language :: Python :: 3
Classifier: Programming Language :: Python :: 3.6
Classifier: Programming Language :: Python :: 3.7
Classifier: Programming Language :: Python :: 3.8
Classifier: Programming Language :: Python :: 3.9
Classifier: Programming Language :: Python :: 3.10
Requires-Python: >=3.6
License-File: LICENSE
Requires-Dist: requests>=2.25.0
Requires-Dist: pytz
Dynamic: author
Dynamic: author-email
Dynamic: classifier
Dynamic: description
Dynamic: description-content-type
Dynamic: home-page
Dynamic: project-url
Dynamic: requires-dist
Dynamic: requires-python
Dynamic: summary
